{"chapter":"guide","sections":{"03B1":"Short introductory articles","03B2":"Classic references","03B3":"Books and online notes","03B4":"Related references on foundations of stacks","03B6":"Papers in the literature","03B5":"Stacks in other fields","05BF":"Higher stacks"},"entries":{"03B1":{"statement":"","proof":null,"section":"Short introductory articles"},"03B2":{"statement":"","proof":null,"section":"Classic references"},"03B3":{"statement":"","proof":null,"section":"Books and online notes"},"03B4":{"statement":"","proof":null,"section":"Related references on foundations of stacks"},"03B6":{"statement":"","proof":null,"section":"Papers in the literature"},"03B5":{"statement":"","proof":null,"section":"Stacks in other fields"},"05BF":{"statement":"","proof":null,"section":"Higher stacks"}}}